odos_python_sdk/__init__.py
odos_python_sdk/api/__init__.py
odos_python_sdk/api/information/__init__.py
odos_python_sdk/api/information/get_chain_ids_info_chains_get.py
odos_python_sdk/api/information/get_contract_info_info_contract_info_version_chain_id_get.py
odos_python_sdk/api/information/get_current_block_info_current_block_chain_id_get.py
odos_python_sdk/api/information/get_executor_info_executor_version_chain_id_get.py
odos_python_sdk/api/information/get_liquidity_sources_info_liquidity_sources_chain_id_get.py
odos_python_sdk/api/information/get_router_info_router_version_chain_id_get.py
odos_python_sdk/api/information/get_token_map_info_tokens_chain_id_get.py
odos_python_sdk/api/pricing/__init__.py
odos_python_sdk/api/pricing/get_chain_token_prices_pricing_token_chain_id_get.py
odos_python_sdk/api/pricing/get_currencies_pricing_currencies_get.py
odos_python_sdk/api/pricing/get_token_price_pricing_token_chain_id_token_addr_get.py
odos_python_sdk/api/smart_order_routing/__init__.py
odos_python_sdk/api/smart_order_routing/assemble_sor_assemble_post.py
odos_python_sdk/api/smart_order_routing/quote_sor_quote_v2_post.py
odos_python_sdk/api/smart_order_routing/quote_zap_sor_quote_v2_zap_post.py
odos_python_sdk/client.py
odos_python_sdk/errors.py
odos_python_sdk/models/__init__.py
odos_python_sdk/models/assemble_path_request.py
odos_python_sdk/models/chain_token_price_map.py
odos_python_sdk/models/chain_token_price_map_tokenprices.py
odos_python_sdk/models/contract_info.py
odos_python_sdk/models/contract_info_erc_20_abi_type_0.py
odos_python_sdk/models/contract_info_router_abi_type_0.py
odos_python_sdk/models/currency_info.py
odos_python_sdk/models/currency_info_list.py
odos_python_sdk/models/current_block_number.py
odos_python_sdk/models/executor_address.py
odos_python_sdk/models/http_validation_error.py
odos_python_sdk/models/liquidity_sources.py
odos_python_sdk/models/path_request_v2.py
odos_python_sdk/models/path_response.py
odos_python_sdk-2.6.1.dist-info/METADATA
odos_python_sdk-2.6.1.dist-info/WHEEL
odos_python_sdk-2.6.1.dist-info/RECORD
